telegraphbot.py
telegraphbot-0.1.dist-info/LICENSE.txt
telegraphbot-0.1.dist-info/METADATA
telegraphbot-0.1.dist-info/WHEEL
telegraphbot-0.1.dist-info/top_level.txt
telegraphbot-0.1.dist-info/RECORD
