Metadata-Version: 2.1
Name: telegraphbot
Version: 0.1
Summary: A tool for python Telegram bots
Home-page: UNKNOWN
License: MIT
Platform: UNKNOWN
Classifier: Programming Language :: Python :: 3
License-File: LICENSE.txt
